LICENSE
README.md
fastapi_apps/__init__.py
fastapi_apps-0.0.1.dist-info/METADATA
fastapi_apps-0.0.1.dist-info/WHEEL
fastapi_apps-0.0.1.dist-info/entry_points.txt
fastapi_apps-0.0.1.dist-info/licenses/LICENSE
fastapi_apps-0.0.1.dist-info/RECORD
