Metadata-Version: 2.4
Name: fastapi-apps
Version: 0.0.1
Summary: Application layer of the FastAPI ecosystem. Provides essential building blocks, utilities, and abstractions that power FastAPI-based projects.
Project-URL: Homepage, https://github.com/fastapi-ecosystem/fastapi-apps
Project-URL: Repository, https://github.com/fastapi-ecosystem/fastapi-apps
Project-URL: Documentation, https://fastapi-ecosystem.github.io/fastapi-apps/
Project-URL: Changelog, https://github.com/fastapi-ecosystem/fastapi-apps/blob/main/CHANGELOG.md
Author-email: Kapil Dagur <kapildagur1306@gmail.com>
Maintainer-email: Kapil Dagur <kapildagur1306@gmail.com>
License-Expression: MIT
License-File: LICENSE
Keywords: apps,fastapi
Classifier: Development Status :: 2 - Pre-Alpha
Classifier: Framework :: FastAPI
Classifier: Intended Audience :: Developers
Classifier: License :: OSI Approved :: MIT License
Classifier: Operating System :: OS Independent
Classifier: Programming Language :: Python :: 3
Classifier: Programming Language :: Python :: 3 :: Only
Classifier: Programming Language :: Python :: 3.10
Classifier: Programming Language :: Python :: 3.11
Classifier: Programming Language :: Python :: 3.12
Classifier: Topic :: Software Development :: Libraries
Classifier: Typing :: Typed
Requires-Python: >=3.10
Requires-Dist: fastapi>=0.116.2
Requires-Dist: pydantic-settings>=2.10.1
